{
  "name": "Edu Flashcard App (Ona Workspace)",
  "build": {
    "context": ".",
    "dockerfile": "Dockerfile"
  },
  "postCreateCommand": "cd backend && npm install && cd ../frontend && npm install",
  "postStartCommand": "bash .devcontainer/start-servers.sh",
  "customizations": {
    "vscode": {
      "extensions": [
        "dbaeumer.vscode-eslint",
        "esbenp.prettier-vscode",
        "ms-vscode.vscode-typescript-next",
        "bradlc.vscode-tailwindcss"
      ]
    }
  },
  "forwardPorts": [3000, 5002],
  "portsAttributes": {
    "3000": {
      "label": "Frontend (React)",
      "onAutoForward": "openPreview"
    },
    "5002": {
      "label": "Backend (API)",
      "onAutoForward": "notify"
    }
  },
  "remoteUser": "node"
}